upper_envelope/__init__.py
upper_envelope/_version.py
upper_envelope/math_funcs.py
upper_envelope/fues_jax/__init__.py
upper_envelope/fues_jax/check_and_scan_funcs.py
upper_envelope/fues_jax/fues_jax.py
upper_envelope/fues_numba/__init__.py
upper_envelope/fues_numba/fues_numba.py
upper_envelope-0.1.3.dist-info/METADATA
upper_envelope-0.1.3.dist-info/WHEEL
upper_envelope-0.1.3.dist-info/licenses/LICENSE
upper_envelope-0.1.3.dist-info/RECORD
