Metadata-Version: 2.4
Name: upper_envelope
Version: 0.1.3
Summary: Upper envelope scan for dynamic discrete-continuous life cycle models.
Project-URL: Github, https://github.com/OpensourceEconomics/upper-envelope
Author-email: Max Blesch <maximilian.blesch@hu-berlin.de>, Sebastian Gsell <gsell.sebastian@gmail.com>
Maintainer-email: Sebastian Gsell <gsell.sebastian@gmail.com>
License: Copyright (c) 2023-2025 The Upper-Envelope Authors
License-File: LICENSE
Keywords: Dynamic programming,Econometrics,Economics,Life cycle models,Statistics
Classifier: Development Status :: 3 - Alpha
Classifier: Intended Audience :: Science/Research
Classifier: License :: OSI Approved :: MIT License
Classifier: Operating System :: MacOS :: MacOS X
Classifier: Operating System :: Microsoft :: Windows
Classifier: Operating System :: POSIX
Classifier: Programming Language :: Python :: 3.10
Classifier: Programming Language :: Python :: 3.11
Classifier: Programming Language :: Python :: 3.12
Classifier: Topic :: Scientific/Engineering
Requires-Python: >=3.10
Requires-Dist: jax
Requires-Dist: numpy
Requires-Dist: pandas
Requires-Dist: scipy
